rl_test_task_2/__init__.py
rl_test_task_2/client.py
rl_test_task_2-0.1.7.dist-info/METADATA
rl_test_task_2-0.1.7.dist-info/WHEEL
rl_test_task_2-0.1.7.dist-info/top_level.txt
rl_test_task_2-0.1.7.dist-info/RECORD
