Metadata-Version: 2.1
Name: rl-test-task-2
Version: 0.1.7
Summary: Task 2
Author: Antonio Corluka
Author-email: antonio.corluka@outlook.com
Requires-Python: >=3.11
Requires-Dist: python-dotenv
Requires-Dist: rl-test-common
Requires-Dist: rl-test-storage-handlers
